deploy_transformers/__init__.py
deploy_transformers/deploy.py
deploy_transformers-0.1.dist-info/LICENSE
deploy_transformers-0.1.dist-info/METADATA
deploy_transformers-0.1.dist-info/WHEEL
deploy_transformers-0.1.dist-info/top_level.txt
deploy_transformers-0.1.dist-info/RECORD
