Metadata-Version: 2.1
Name: deploy-transformers
Version: 0.1
Summary: Easily deploy HuggingFace Transformers on a website
Home-page: https://github.com/aquadzn/deploy-transformers
Author: William Jacques
Author-email: williamjcqs8@gmail.com
License: UNKNOWN
Platform: UNKNOWN
Classifier: Programming Language :: Python :: 3
Classifier: License :: OSI Approved :: Apache Software License
Classifier: Operating System :: OS Independent
Requires-Python: >=3.5
Requires-Dist: starlette
Requires-Dist: uvicorn
Requires-Dist: jinja2
Requires-Dist: aiofiles
